expertai/nlapi/cloud/__init__.py
expertai/nlapi/cloud/__version__.py
expertai/nlapi/cloud/client.py
expertai/nlapi/cloud/object_mapper.py
expertai/nlapi/cloud/request.py
expertai/nlapi/cloud/response.py
expertai/nlapi/cloud/validate.py
expertai/nlapi/common/__init__.py
expertai/nlapi/common/authentication.py
expertai/nlapi/common/constants.py
expertai/nlapi/common/errors.py
expertai/nlapi/common/model/__init__.py
expertai/nlapi/common/model/atom.py
expertai/nlapi/common/model/category.py
expertai/nlapi/common/model/context.py
expertai/nlapi/common/model/data_model.py
expertai/nlapi/common/model/dependency.py
expertai/nlapi/common/model/entity.py
expertai/nlapi/common/model/eproperty.py
expertai/nlapi/common/model/extraction.py
expertai/nlapi/common/model/iptc.py
expertai/nlapi/common/model/knowledge.py
expertai/nlapi/common/model/language.py
expertai/nlapi/common/model/main_lemma.py
expertai/nlapi/common/model/main_phrase.py
expertai/nlapi/common/model/main_sentence.py
expertai/nlapi/common/model/main_syncon.py
expertai/nlapi/common/model/paragraph.py
expertai/nlapi/common/model/phrase.py
expertai/nlapi/common/model/position.py
expertai/nlapi/common/model/relation.py
expertai/nlapi/common/model/sentence.py
expertai/nlapi/common/model/sentiment.py
expertai/nlapi/common/model/standard.py
expertai/nlapi/common/model/taxonomy.py
expertai/nlapi/common/model/template.py
expertai/nlapi/common/model/token.py
expertai/nlapi/common/model/topic.py
expertai/nlapi/common/model/vsyncon.py
expertai/nlapi/edge/__init__.py
expertai/nlapi/edge/__version__.py
expertai/nlapi/edge/client.py
expertai/nlapi/edge/object_mapper.py
expertai/nlapi/edge/request.py
expertai/nlapi/edge/response.py
expertai/nlapi/edge/validate.py
expertai/nlapi/v1/__init__.py
expertai/nlapi/v1/__version__.py
expertai/nlapi/v1/authentication.py
expertai/nlapi/v1/client.py
expertai/nlapi/v1/constants.py
expertai/nlapi/v1/errors.py
expertai/nlapi/v1/object_mapper.py
expertai/nlapi/v1/request.py
expertai_nlapi-2.5.0.dist-info/LICENSE
expertai_nlapi-2.5.0.dist-info/METADATA
expertai_nlapi-2.5.0.dist-info/WHEEL
expertai_nlapi-2.5.0.dist-info/top_level.txt
expertai_nlapi-2.5.0.dist-info/RECORD
