Metadata-Version: 2.1
Name: expertai-nlapi
Version: 2.5.0
Summary: Python client for expert.ai Natural Language API
Home-page: https://github.com/therealexpertai/nlapi-python
Author: Expert.ai S.p.A.
Author-email: api.support@expert.ai
License: Apache License 2.0
Classifier: Development Status :: 4 - Beta
Classifier: Programming Language :: Python :: 3
Classifier: License :: OSI Approved :: Apache Software License
Classifier: Operating System :: OS Independent
Classifier: Topic :: Text Processing :: Linguistic
Classifier: Intended Audience :: Developers
Classifier: Intended Audience :: Science/Research
Classifier: Intended Audience :: Education
Requires-Python: >=3.7
License-File: LICENSE
